say_week1_knn/__init__.py
say_week1_knn/kr_main.py
say_week1_knn/main.py
say_week1_knn-0.1.0.dist-info/METADATA
say_week1_knn-0.1.0.dist-info/WHEEL
say_week1_knn-0.1.0.dist-info/entry_points.txt
say_week1_knn-0.1.0.dist-info/top_level.txt
say_week1_knn-0.1.0.dist-info/RECORD
