Metadata-Version: 2.1
Name: say-week1-knn
Version: 0.1.0
Summary: Week1 program - using scikit-learn KNeighborsClassifier
Author-email: NishNovae <raecrowned@gmail.com>
License: MIT
Project-URL: Homepage, https://github.com/NishNovae/say-week1-knn
Project-URL: Issues, https://github.com/NishNovae/say-week1-knn/issues
Requires-Python: >=3.8
Requires-Dist: scikit-learn>=1.3.2
